pyHilbertSort.cp37-win_amd64.pyd
pyHilbertSort-1.0.2.dist-info/METADATA
pyHilbertSort-1.0.2.dist-info/WHEEL
pyHilbertSort-1.0.2.dist-info/top_level.txt
pyHilbertSort-1.0.2.dist-info/RECORD
