Metadata-Version: 2.1
Name: pyHilbertSort
Version: 1.0.2
Summary: A light-weight hilbert curve sorting library for point and mesh
Home-page: https://github.com/BinWang0213/HilbertSort
Author: Bin Wang
Author-email: binwang.0213@gmail.com
License: UNKNOWN
Platform: UNKNOWN
